[
  {
    "id": "iv-1",
    "influencer_name": "Sarah Kim",
    "influencer_handle": "@sarahkbeauty",
    "video_url": "https://www.w3schools.com/html/movie.mp4",
    "thumbnail_url": "https://images.pexels.com/photos/3785079/pexels-photo-3785079.jpeg?auto=compress&cs=tinysrgb&w=400&h=711",
    "caption": "My morning skincare routine with Consumer Innovations essentials ✨",
    "instagram_link": "https://instagram.com/sarahkbeauty",
    "views": "125K",
    "display_order": 1,
    "active": true
  },
  {
    "id": "iv-2",
    "influencer_name": "Jessica Park",
    "influencer_handle": "@jessglowup",
    "video_url": "https://www.w3schools.com/html/mov_bbb.mp4",
    "thumbnail_url": "https://images.pexels.com/photos/3812743/pexels-photo-3812743.jpeg?auto=compress&cs=tinysrgb&w=400&h=711",
    "caption": "Glass skin achieved with these Korean products! 🧴",
    "instagram_link": "https://instagram.com/jessglowup",
    "views": "89K",
    "display_order": 2,
    "active": true
  },
  {
    "id": "iv-3",
    "influencer_name": "MinJi Lee",
    "influencer_handle": "@minjibeauty",
    "video_url": "https://www.w3schools.com/html/movie.mp4",
    "thumbnail_url": "https://images.pexels.com/photos/3785079/pexels-photo-3785079.jpeg?auto=compress&cs=tinysrgb&w=400&h=711",
    "caption": "GRWM: Full face using only Korean beauty products 💄",
    "instagram_link": "https://instagram.com/minjibeauty",
    "views": "210K",
    "display_order": 3,
    "active": true
  },
  {
    "id": "iv-4",
    "influencer_name": "Emma Choi",
    "influencer_handle": "@emmaskinsecrets",
    "video_url": "https://www.w3schools.com/html/mov_bbb.mp4",
    "thumbnail_url": "https://images.pexels.com/photos/3812743/pexels-photo-3812743.jpeg?auto=compress&cs=tinysrgb&w=400&h=711",
    "caption": "My favorite Korean sunscreen review ☀️",
    "instagram_link": "https://instagram.com/emmaskinsecrets",
    "views": "156K",
    "display_order": 4,
    "active": true
  },
  {
    "id": "iv-5",
    "influencer_name": "Lily Chen",
    "influencer_handle": "@lilyglows",
    "video_url": "https://www.w3schools.com/html/movie.mp4",
    "thumbnail_url": "https://images.pexels.com/photos/3785079/pexels-photo-3785079.jpeg?auto=compress&cs=tinysrgb&w=400&h=711",
    "caption": "Korean skincare haul + first impressions 🛍️",
    "instagram_link": "https://instagram.com/lilyglows",
    "views": "94K",
    "display_order": 5,
    "active": true
  },
  {
    "id": "iv-6",
    "influencer_name": "Sophie Yoon",
    "influencer_handle": "@sophieglowsup",
    "video_url": "https://www.w3schools.com/html/mov_bbb.mp4",
    "thumbnail_url": "https://images.pexels.com/photos/3762876/pexels-photo-3762876.jpeg?auto=compress&cs=tinysrgb&w=400&h=711",
    "caption": "Testing viral Korean skincare products for a week 💫",
    "instagram_link": "https://instagram.com/sophieglowsup",
    "views": "178K",
    "display_order": 6,
    "active": true
  },
  {
    "id": "iv-7",
    "influencer_name": "Grace Han",
    "influencer_handle": "@gracefulbeauty",
    "video_url": "https://www.w3schools.com/html/movie.mp4",
    "thumbnail_url": "https://images.pexels.com/photos/3997989/pexels-photo-3997989.jpeg?auto=compress&cs=tinysrgb&w=400&h=711",
    "caption": "Affordable Consumer Innovations dupes you need to try!",
    "instagram_link": "https://instagram.com/gracefulbeauty",
    "views": "142K",
    "display_order": 7,
    "active": true
  },
  {
    "id": "iv-8",
    "influencer_name": "Mia Song",
    "influencer_handle": "@miaskincare",
    "video_url": "https://www.w3schools.com/html/mov_bbb.mp4",
    "thumbnail_url": "https://images.pexels.com/photos/3785147/pexels-photo-3785147.jpeg?auto=compress&cs=tinysrgb&w=400&h=711",
    "caption": "10-step Korean skincare routine explained 🌟",
    "instagram_link": "https://instagram.com/miaskincare",
    "views": "302K",
    "display_order": 8,
    "active": true
  },
  {
    "id": "iv-9",
    "influencer_name": "Aria Kang",
    "influencer_handle": "@ariabeautyfix",
    "video_url": "https://www.w3schools.com/html/movie.mp4",
    "thumbnail_url": "https://images.pexels.com/photos/3812742/pexels-photo-3812742.jpeg?auto=compress&cs=tinysrgb&w=400&h=711",
    "caption": "Night skincare routine for glowing skin ✨",
    "instagram_link": "https://instagram.com/ariabeautyfix",
    "views": "198K",
    "display_order": 9,
    "active": true
  },
  {
    "id": "iv-10",
    "influencer_name": "Hannah Jo",
    "influencer_handle": "@hannahjo_beauty",
    "video_url": "https://www.w3schools.com/html/mov_bbb.mp4",
    "thumbnail_url": "https://images.pexels.com/photos/3865676/pexels-photo-3865676.jpeg?auto=compress&cs=tinysrgb&w=400&h=711",
    "caption": "Best Korean sheet masks for every skin type 🎭",
    "instagram_link": "https://instagram.com/hannahjo_beauty",
    "views": "167K",
    "display_order": 10,
    "active": true
  },
  {
    "id": "iv-11",
    "influencer_name": "Chloe Bae",
    "influencer_handle": "@chloebaeglow",
    "video_url": "https://www.w3schools.com/html/movie.mp4",
    "thumbnail_url": "https://images.pexels.com/photos/3762283/pexels-photo-3762283.jpeg?auto=compress&cs=tinysrgb&w=400&h=711",
    "caption": "Consumer Innovations secrets from Seoul beauty experts 🇰🇷",
    "instagram_link": "https://instagram.com/chloebaeglow",
    "views": "234K",
    "display_order": 11,
    "active": true
  },
  {
    "id": "iv-12",
    "influencer_name": "Olivia Shin",
    "influencer_handle": "@oliviaskinfix",
    "video_url": "https://www.w3schools.com/html/mov_bbb.mp4",
    "thumbnail_url": "https://images.pexels.com/photos/3785074/pexels-photo-3785074.jpeg?auto=compress&cs=tinysrgb&w=400&h=711",
    "caption": "How I cleared my acne with Korean skincare 💚",
    "instagram_link": "https://instagram.com/oliviaskinfix",
    "views": "387K",
    "display_order": 12,
    "active": true
  },
  {
    "id": "iv-13",
    "influencer_name": "Zoey Park",
    "influencer_handle": "@zoeypark_glow",
    "video_url": "https://www.w3schools.com/html/movie.mp4",
    "thumbnail_url": "https://images.pexels.com/photos/3762292/pexels-photo-3762292.jpeg?auto=compress&cs=tinysrgb&w=400&h=711",
    "caption": "Korean makeup look using only Consumer Innovations brands 💄",
    "instagram_link": "https://instagram.com/zoeypark_glow",
    "views": "276K",
    "display_order": 13,
    "active": true
  },
  {
    "id": "iv-14",
    "influencer_name": "Bella Hwang",
    "influencer_handle": "@bellahwang",
    "video_url": "https://www.w3schools.com/html/mov_bbb.mp4",
    "thumbnail_url": "https://images.pexels.com/photos/3865675/pexels-photo-3865675.jpeg?auto=compress&cs=tinysrgb&w=400&h=711",
    "caption": "Summer Consumer Innovations essentials for oily skin 🌞",
    "instagram_link": "https://instagram.com/bellahwang",
    "views": "118K",
    "display_order": 14,
    "active": true
  },
  {
    "id": "iv-15",
    "influencer_name": "Rachel Moon",
    "influencer_handle": "@rachelmoon_beauty",
    "video_url": "https://www.w3schools.com/html/movie.mp4",
    "thumbnail_url": "https://images.pexels.com/photos/3373736/pexels-photo-3373736.jpeg?auto=compress&cs=tinysrgb&w=400&h=711",
    "caption": "Consumer Innovations starter kit: What to buy first 🎁",
    "instagram_link": "https://instagram.com/rachelmoon_beauty",
    "views": "203K",
    "display_order": 15,
    "active": true
  }
]
